{"head":{"title":"reduceInitial","layout":"Optimisation","identifier":"reduceInitial","description":"Replaces the CSS initial keyword with the actual value, when the resulting output is smaller."},"body":"<p>Replaces the CSS <code>initial</code> keyword with the <em>actual</em> value, when the resulting output is smaller.</p>\n","__filename":"optimisations/reduceInitial.md","__url":"/optimisations/reduceInitial/","__resourceUrl":"/optimisations/reduceInitial/index.html","__dataUrl":"/optimisations/reduceInitial/index.html.0ccd7bfa16c4240cf17886512cc039a0.json"}